mpax/__init__.py
mpax/feasibility_polishing.py
mpax/iteration_stats_utils.py
mpax/loop_utils.py
mpax/mp_io.py
mpax/preprocess.py
mpax/r2hpdhg.py
mpax/rapdhg.py
mpax/restart.py
mpax/solver_log.py
mpax/termination.py
mpax/utils.py
mpax-0.2.4.dist-info/LICENSE
mpax-0.2.4.dist-info/METADATA
mpax-0.2.4.dist-info/WHEEL
mpax-0.2.4.dist-info/RECORD
