Metadata-Version: 2.3
Name: mpax
Version: 0.2.4
Summary: MPAX: Mathematical Programming in JAX
License: MIT
Author: Zedong Peng
Author-email: zdpeng95@gmail.com
Requires-Python: >=3.10
Classifier: License :: OSI Approved :: MIT License
Classifier: Programming Language :: Python :: 3
Classifier: Programming Language :: Python :: 3.10
Classifier: Programming Language :: Python :: 3.11
Classifier: Programming Language :: Python :: 3.12
Classifier: Programming Language :: Python :: 3.13
Requires-Dist: chex (>=0.1.87)
Requires-Dist: jax (==0.4.38) ; sys_platform == "darwin" and platform_machine == "x86_64"
Requires-Dist: jax (>=0.5.3) ; sys_platform != "darwin" or platform_machine != "x86_64"
Requires-Dist: numpy (>1.24.4)
